{
  "locations": [
    {
      "name": "Track 2",
      "id": 26001,
      "conference": "DC26",
      "updated_at": "2018-06-30T18:57+0000"
    },
    {
      "name": "101 Track, Flamingo",
      "id": 26002,
      "conference": "DC26",
      "updated_at": "2018-06-30T18:57+0000"
    },
    {
      "name": "Track 1",
      "id": 26003,
      "conference": "DC26",
      "updated_at": "2018-06-30T18:57+0000"
    },
    {
      "name": "Track 3",
      "id": 26004,
      "conference": "DC26",
      "updated_at": "2018-06-30T18:57+0000"
    },
    {
      "name": "Location:TBA",
      "id": 26005,
      "conference": "DC26",
      "updated_at": "2018-06-30T18:57+0000"
    },
    {
      "name": "Icon F",
      "id": 26006,
      "conference": "DC26",
      "updated_at": "2018-07-02T15:05+0000"
    },
    {
      "name": "Icon D",
      "id": 26007,
      "conference": "DC26",
      "updated_at": "2018-07-02T15:05+0000"
    },
    {
      "name": "Icon B",
      "id": 26008,
      "conference": "DC26",
      "updated_at": "2018-07-02T15:05+0000"
    },
    {
      "name": "Icon C",
      "id": 26009,
      "conference": "DC26",
      "updated_at": "2018-07-02T15:05+0000"
    },
    {
      "name": "Icon E",
      "id": 26010,
      "conference": "DC26",
      "updated_at": "2018-07-02T15:05+0000"
    },
    {
      "name": "Icon A",
      "id": 26011,
      "conference": "DC26",
      "updated_at": "2018-07-02T15:05+0000"
    },
    {
      "name": "Demo Labs",
      "id": 26012,
      "conference": "DC26",
      "updated_at": "2018-07-02T23:44+0000"
    },
    {
      "name": "Location In Description",
      "id": 26013,
      "conference": "DC26",
      "updated_at": "2018-07-21T22:43+0000"
    },
    {
      "name": "Skytalks",
      "id": 26014,
      "conference": "DC26",
      "updated_at": "2018-07-30T23:26+0000"
    }
  ],
  "updated_at": "2018-07-30T23:26+0000"
}